atum.py
atum-0.3.0.post1.dist-info/METADATA
atum-0.3.0.post1.dist-info/RECORD
atum-0.3.0.post1.dist-info/WHEEL
atum-0.3.0.post1.dist-info/top_level.txt
