Metadata-Version: 2.1
Name: atum
Version: 0.3.0-1
Summary: Erlang-like atoms in Python 3
Home-page: https://github.com/hiway/atum
Author: Harshad Sharma
Author-email: harshad@sharma.io
License: MIT
Platform: UNKNOWN
Classifier: Development Status :: 4 - Beta
Classifier: Intended Audience :: Developers
Classifier: License :: OSI Approved :: MIT License
Classifier: Programming Language :: Python
Classifier: Topic :: Software Development
Classifier: Topic :: Utilities
Provides-Extra: dev
Provides-Extra: dev
Requires-Dist: twine; extra == 'dev'
Requires-Dist: pypandoc; extra == 'dev'
Requires-Dist: pytest; extra == 'dev'
Requires-Dist: pytest-cov; extra == 'dev'
